bcn_rainfall_api_client/__init__.py
bcn_rainfall_api_client/client.py
bcn_rainfall_api_client-1.0.9.dist-info/METADATA
bcn_rainfall_api_client-1.0.9.dist-info/WHEEL
bcn_rainfall_api_client-1.0.9.dist-info/top_level.txt
bcn_rainfall_api_client-1.0.9.dist-info/RECORD
