Metadata-Version: 2.4
Name: bcn-rainfall-api-client
Version: 1.0.9
Summary: Client who serves routes from the Barcelona Rainfall API.
Author-email: Paul Charles <paul.charles@tutanota.com>
Requires-Python: >=3.12
Requires-Dist: api-session~=1.4.2
Requires-Dist: pre-commit~=4.0.1
Requires-Dist: pydantic~=2.8.2
Requires-Dist: pyyaml~=6.0.2
